cdosolve/__init__.py
cdosolve/_version.py
cdosolve-0.0.1.dist-info/LICENSE
cdosolve-0.0.1.dist-info/METADATA
cdosolve-0.0.1.dist-info/WHEEL
cdosolve-0.0.1.dist-info/top_level.txt
cdosolve-0.0.1.dist-info/RECORD
