Metadata-Version: 2.1
Name: cdosolve
Version: 0.0.1
License: Apache Licence 2.0
Keywords: finance risk quantitative
Platform: any
Classifier: Topic :: Scientific/Engineering :: Mathematics
Classifier: Topic :: Office/Business :: Financial
Classifier: Topic :: Software Development :: Libraries
Classifier: Intended Audience :: Developers
Classifier: Intended Audience :: Science/Research
Classifier: License :: OSI Approved :: Apache Software License
Classifier: Programming Language :: Python :: 3
Requires-Python: >=3.9
License-File: LICENSE
Requires-Dist: numpy >=1.25
Requires-Dist: scipy >=1.11
